inewave/__init__.py
inewave/config.py
inewave/py.typed
inewave/_utils/__init__.py
inewave/_utils/formatacao.py
inewave/libs/__init__.py
inewave/libs/eolica.py
inewave/libs/restricoes.py
inewave/libs/usinas_hidreletricas.py
inewave/libs/modelos/__init__.py
inewave/libs/modelos/eolica.py
inewave/libs/modelos/restricoes.py
inewave/libs/modelos/usinas_hidreletricas.py
inewave/newave/__init__.py
inewave/newave/abertura.py
inewave/newave/adterm.py
inewave/newave/agrint.py
inewave/newave/arquivos.py
inewave/newave/avl_cortesfpha_nwv.py
inewave/newave/avl_desvfpha_s.py
inewave/newave/avl_desvfpha_v_q.py
inewave/newave/bid.py
inewave/newave/cadic.py
inewave/newave/caso.py
inewave/newave/clasgas.py
inewave/newave/clast.py
inewave/newave/confhd.py
inewave/newave/conft.py
inewave/newave/cortes.py
inewave/newave/cortesh.py
inewave/newave/curva.py
inewave/newave/cvar.py
inewave/newave/dger.py
inewave/newave/dsvagua.py
inewave/newave/eafpast.py
inewave/newave/eco_fpha.py
inewave/newave/eliminacao_cortes.py
inewave/newave/elnino.py
inewave/newave/enavazb.py
inewave/newave/enavazf.py
inewave/newave/energiab.py
inewave/newave/energiaf.py
inewave/newave/energias.py
inewave/newave/engnat.py
inewave/newave/ensoaux.py
inewave/newave/evap_avl_desv.py
inewave/newave/evap_cortes.py
inewave/newave/evap_eco.py
inewave/newave/exph.py
inewave/newave/expt.py
inewave/newave/forward.py
inewave/newave/forwarh.py
inewave/newave/fpha_avl_desv_s.py
inewave/newave/fpha_avl_desv_v_q.py
inewave/newave/fpha_cortes.py
inewave/newave/fpha_eco.py
inewave/newave/gee.py
inewave/newave/ghmin.py
inewave/newave/gtminpat.py
inewave/newave/hidr.py
inewave/newave/itaipu.py
inewave/newave/manutt.py
inewave/newave/modif.py
inewave/newave/newavetim.py
inewave/newave/nwv_avl_evap.py
inewave/newave/nwv_cortes_evap.py
inewave/newave/nwv_eco_evap.py
inewave/newave/parp.py
inewave/newave/parpeol.py
inewave/newave/parpvaz.py
inewave/newave/patamar.py
inewave/newave/penalid.py
inewave/newave/perda.py
inewave/newave/pmo.py
inewave-1.11.2.dist-info/METADATA
inewave-1.11.2.dist-info/WHEEL
inewave-1.11.2.dist-info/licenses/LICENSE.md
inewave-1.11.2.dist-info/RECORD
